ksql/__init__.py
ksql/api.py
ksql/builder.py
ksql/client.py
ksql/errors.py
ksql/upload.py
ksql/utils.py
ksql_python_ng-0.29.0.1.dist-info/LICENSE
ksql_python_ng-0.29.0.1.dist-info/METADATA
ksql_python_ng-0.29.0.1.dist-info/WHEEL
ksql_python_ng-0.29.0.1.dist-info/top_level.txt
ksql_python_ng-0.29.0.1.dist-info/RECORD
