Metadata-Version: 2.1
Name: ksql-python-ng
Version: 0.29.0.1
Summary: A Python wrapper for the KSQL REST API
Home-page: https://github.com/sheinbergon/ksql-python-ng
Author: Bryan Yang
Author-email: kenshin200528@gmail.com
Maintainer: Idan Sheinberg
Maintainer-email: ishinberg0@gmail.com
License: MIT License
Platform: any
Classifier: Development Status :: 5 - Production/Stable
Classifier: Intended Audience :: Developers
Classifier: Natural Language :: English
Classifier: License :: OSI Approved :: MIT License
Classifier: Programming Language :: Python
Classifier: Programming Language :: Python :: 3.9
Classifier: Programming Language :: Python :: 3.10
Classifier: Programming Language :: Python :: 3.11
Classifier: Topic :: Software Development :: Libraries :: Python Modules
License-File: LICENSE
Requires-Dist: requests
Requires-Dist: six
Requires-Dist: httpx[http2]
Provides-Extra: dev
Requires-Dist: nose ==1.3.7 ; extra == 'dev'
Requires-Dist: codecov ; extra == 'dev'
Requires-Dist: coverage ; extra == 'dev'
Requires-Dist: confluent-kafka[avro] ==2.4.0 ; extra == 'dev'
Requires-Dist: urllib3 ==1.26.19 ; extra == 'dev'
Requires-Dist: responses ; extra == 'dev'
